nta/__init__.py
nta/cli.py
nta/data.py
nta/dataset/__init__.py
nta/dataset/iscx_vpn_2016.py
nta/test/__init__.py
nta_tools-0.0.2.dist-info/LICENSE
nta_tools-0.0.2.dist-info/METADATA
nta_tools-0.0.2.dist-info/WHEEL
nta_tools-0.0.2.dist-info/top_level.txt
nta_tools-0.0.2.dist-info/zip-safe
nta_tools-0.0.2.dist-info/RECORD
