Metadata-Version: 2.1
Name: nta-tools
Version: 0.0.2
Summary: A collection of network traffic analysis tools.
Home-page: https://github.com/well-shark/nta
Author: WellShark
Author-email: wellshark.net@gmail.com
License: MIT
Platform: UNKNOWN
Classifier: Development Status :: 1 - Planning
Classifier: Programming Language :: Python :: 3
Classifier: License :: OSI Approved :: MIT License
Classifier: Operating System :: OS Independent
Requires-Python: >=3.6.0
License-File: LICENSE
Requires-Dist: numpy
Requires-Dist: pandas
Requires-Dist: tqdm
Requires-Dist: nfstream
